ansible_forum_events/__init__.py
ansible_forum_events-0.1.0.dist-info/entry_points.txt
ansible_forum_events-0.1.0.dist-info/licenses/LICENSE
ansible_forum_events-0.1.0.dist-info/WHEEL
ansible_forum_events-0.1.0.dist-info/METADATA
ansible_forum_events-0.1.0.dist-info/RECORD
