Metadata-Version: 2.4
Name: ansible-forum-events
Version: 0.1.0
Summary: Prints out the upcoming Ansible Forum events from the forum API in markdown format.
Author-email: Anwesha Das <anwesha.srkr@gmail.com>
License-Expression: GPL-3.0-or-later
License-File: LICENSE
Requires-Dist: httpx
Project-URL: Home, https://github.com/anweshadas/ansible-forum-events
